hypermodule/__init__.py
hypermodule/hypermodule.py
hypermodule/partials.py
hypermodule/utils.py
hypermodule-0.1.2.dist-info/LICENSE
hypermodule-0.1.2.dist-info/METADATA
hypermodule-0.1.2.dist-info/WHEEL
hypermodule-0.1.2.dist-info/top_level.txt
hypermodule-0.1.2.dist-info/RECORD
