Metadata-Version: 2.1
Name: hypermodule
Version: 0.1.2
Summary: Wrapper for managing neural network training processes
Home-page: https://github.com/kevinkevin556/HyperModule
Author: Zhen-Lun Hong
Author-email: kevink556@gmail.com
License: MIT
Platform: UNKNOWN
Classifier: Development Status :: 3 - Alpha
Classifier: Intended Audience :: Developers
Classifier: License :: OSI Approved :: MIT License
Classifier: Programming Language :: Python :: 3
Classifier: Programming Language :: Python :: 3.6
Classifier: Programming Language :: Python :: 3.7
Classifier: Programming Language :: Python :: 3.8
Classifier: Programming Language :: Python :: 3.9
Classifier: Programming Language :: Python :: 3.10
Requires-Dist: torch (>=2.0.1)
Requires-Dist: matplotlib
Requires-Dist: numpy
Requires-Dist: tqdm
